{
	"datasegment":"",
	
	"1":"",
	"2":"",
	"3":[
		{
			"name":"main",
			"return":"int",
			"body":[]
		}
	],
	"4":[
		{
			"name":"main",
			"return":"int",
			"body":[
				{
					"type":"int",
					"name":"a",
					"value":"5",
					"size":"8"
				}
			]
		}
	],
	"5":[
		{
			"name":"main",
			"return":"int",
			"body":[
				{
					"type":"int",
					"name":"a",
					"value":"5",
					"size":"8"
				},
				{
					"type":"int",
					"name":"b",
					"value":"10",
					"size":"8"
				}
			]
		}
	],
	"6":[
		{
			"name":"main",
			"return":"int",
			"body":[
				{
					"type":"int",
					"name":"a",
					"value":"5",
					"size":"8"
				},
				{
					"type":"int",
					"name":"b",
					"value":"10",
					"size":"8"
				},
				{
					"type":"int",
					"name":"ans",
					"value":"0",
					"size":"8"
				}
			]
		}
	],
	"7":[
		{
			"name":"main",
			"return":"int",
			"body":[
				{
					"type":"int",
					"name":"a",
					"value":"5",
					"size":"8"
				},
				{
					"type":"int",
					"name":"b",
					"value":"10",
					"size":"8"
				},
				{
					"type":"int",
					"name":"ans",
					"value":"0",
					"size":"8"
				}
			]
		},
		{
			"name":"sum",
			"return":"int",
			"body":[]
		}
	],
	"11":[
		{
			"name":"main",
			"return":"int",
			"body":[
				{
					"type":"int",
					"name":"a",
					"value":"5",
					"size":"8"
				},
				{
					"type":"int",
					"name":"b",
					"value":"10",
					"size":"8"
				},
				{
					"type":"int",
					"name":"ans",
					"value":"0",
					"size":"8"
				}
			]
		},
		{
			"name":"sum",
			"return":"int",
			"body":[
				{
					"type":"int",
					"name":"x",
					"value":"5",
					"size":"8"
				},
				{
					"type":"int",
					"name":"y",
					"value":"10",
					"size":"8"
				}
			]
		}
	],
	"12":[
		{
			"name":"main",
			"return":"int",
			"body":[
				{
					"type":"int",
					"name":"a",
					"value":"5",
					"size":"8"
				},
				{
					"type":"int",
					"name":"b",
					"value":"10",
					"size":"8"
				},
				{
					"type":"int",
					"name":"ans",
					"value":"15",
					"size":"8"
				}
			]
		}
	],
	"9":""
}
